pvaccess/.__init__.py.un~
pvaccess/Com.dll
pvaccess/__init__.py
pvaccess/__init__.py~
pvaccess/boost_container-vc142-mt-x64-1_87.dll
pvaccess/boost_graph-vc142-mt-x64-1_87.dll
pvaccess/boost_numpy313-vc142-mt-x64-1_87.dll
pvaccess/boost_python313-vc142-mt-x64-1_87.dll
pvaccess/ca.dll
pvaccess/dbCore.dll
pvaccess/dbRecStd.dll
pvaccess/nt.dll
pvaccess/pvAccess.dll
pvaccess/pvAccessCA.dll
pvaccess/pvAccessIOC.dll
pvaccess/pvData.dll
pvaccess/pvDatabase.dll
pvaccess/pvaClient.dll
pvaccess/pvaccess.pyd
pvaccess/qsrv.dll
pvaccess/dbd/PVAClientRegister.dbd
pvaccess/dbd/PVACommonRegister.dbd
pvaccess/dbd/PVAServerRegister.dbd
pvaccess/dbd/aSubRecord.dbd
pvaccess/dbd/aaiRecord.dbd
pvaccess/dbd/aaoRecord.dbd
pvaccess/dbd/aiRecord.dbd
pvaccess/dbd/aoRecord.dbd
pvaccess/dbd/asSub.dbd
pvaccess/dbd/base.dbd
pvaccess/dbd/biRecord.dbd
pvaccess/dbd/boRecord.dbd
pvaccess/dbd/bptTypeJdegC.dbd
pvaccess/dbd/bptTypeJdegF.dbd
pvaccess/dbd/bptTypeKdegC.dbd
pvaccess/dbd/bptTypeKdegF.dbd
pvaccess/dbd/calcRecord.dbd
pvaccess/dbd/calcoutRecord.dbd
pvaccess/dbd/compressRecord.dbd
pvaccess/dbd/dbCommon.dbd
pvaccess/dbd/dbCore.dbd
pvaccess/dbd/devSoft.dbd
pvaccess/dbd/dfanoutRecord.dbd
pvaccess/dbd/dlload.dbd
pvaccess/dbd/eventRecord.dbd
pvaccess/dbd/fanoutRecord.dbd
pvaccess/dbd/filters.dbd
pvaccess/dbd/histogramRecord.dbd
pvaccess/dbd/int64inRecord.dbd
pvaccess/dbd/int64outRecord.dbd
pvaccess/dbd/links.dbd
pvaccess/dbd/longinRecord.dbd
pvaccess/dbd/longoutRecord.dbd
pvaccess/dbd/lsiRecord.dbd
pvaccess/dbd/lsoRecord.dbd
pvaccess/dbd/mbbiDirectRecord.dbd
pvaccess/dbd/mbbiRecord.dbd
pvaccess/dbd/mbboDirectRecord.dbd
pvaccess/dbd/mbboRecord.dbd
pvaccess/dbd/menuAlarmSevr.dbd
pvaccess/dbd/menuAlarmStat.dbd
pvaccess/dbd/menuConvert.dbd
pvaccess/dbd/menuFtype.dbd
pvaccess/dbd/menuGlobal.dbd
pvaccess/dbd/menuIvoa.dbd
pvaccess/dbd/menuOmsl.dbd
pvaccess/dbd/menuPini.dbd
pvaccess/dbd/menuPost.dbd
pvaccess/dbd/menuPriority.dbd
pvaccess/dbd/menuScan.dbd
pvaccess/dbd/menuSimm.dbd
pvaccess/dbd/menuYesNo.dbd
pvapy-5.6.0.dist-info/METADATA
pvapy-5.6.0.dist-info/WHEEL
pvapy-5.6.0.dist-info/entry_points.txt
pvapy-5.6.0.dist-info/top_level.txt
pvapy-5.6.0.dist-info/RECORD
