Metadata-Version: 2.2
Name: pvapy
Version: 5.6.0
Summary: Python library for EPICS PV Access
Home-page: https://github.com/epics-base/pvaPy
License: EPICS Open License
Requires-Dist: numpy<1.21,>=1.19; python_version < "3.8"
Requires-Dist: numpy<2.0,>=1.22; python_version >= "3.8" and python_version < "3.9"
Requires-Dist: numpy>=2.0; python_version >= "3.9" and python_version < "3.13"
Requires-Dist: numpy>=2.1; python_version >= "3.13"
Provides-Extra: image-processing
Requires-Dist: pillow; extra == "image-processing"
Requires-Dist: h5py; extra == "image-processing"
Requires-Dist: hdf5plugin; extra == "image-processing"
Provides-Extra: encryption
Requires-Dist: pycryptodome; extra == "encryption"
Requires-Dist: rsa; extra == "encryption"
Provides-Extra: blosc-compression
Requires-Dist: blosc; extra == "blosc-compression"
Provides-Extra: lz4-compression
Requires-Dist: lz4; extra == "lz4-compression"
Provides-Extra: bslz4-compression
Requires-Dist: bitshuffle; extra == "bslz4-compression"
Provides-Extra: all
Requires-Dist: pillow; extra == "all"
Requires-Dist: h5py; extra == "all"
Requires-Dist: hdf5plugin; extra == "all"
Requires-Dist: pycryptodome; extra == "all"
Requires-Dist: rsa; extra == "all"
Requires-Dist: blosc; extra == "all"
Requires-Dist: lz4; extra == "all"
Requires-Dist: bitshuffle; extra == "all"
Dynamic: description
Dynamic: description-content-type
Dynamic: home-page
Dynamic: license
Dynamic: provides-extra
Dynamic: requires-dist
Dynamic: summary
